pywis_pubsub/__init__.py
pywis_pubsub/cli_options.py
pywis_pubsub/errors.py
pywis_pubsub/ets.py
pywis_pubsub/geometry.py
pywis_pubsub/hook.py
pywis_pubsub/kpi.py
pywis_pubsub/message.py
pywis_pubsub/mqtt.py
pywis_pubsub/publish.py
pywis_pubsub/schema.py
pywis_pubsub/storage.py
pywis_pubsub/subscribe.py
pywis_pubsub/util.py
pywis_pubsub/verification.py
pywis_pubsub-0.11.0.dist-info/licenses/LICENSE
pywis_pubsub-0.11.0.dist-info/METADATA
pywis_pubsub-0.11.0.dist-info/WHEEL
pywis_pubsub-0.11.0.dist-info/entry_points.txt
pywis_pubsub-0.11.0.dist-info/top_level.txt
pywis_pubsub-0.11.0.dist-info/RECORD
