Metadata-Version: 2.4
Name: pywis-pubsub
Version: 0.11.0
Summary: pywis-pubsub provides subscription and download capability of WMO data from WIS2 infrastructure services
Home-page: https://github.com/World-Meteorological-Organization/pywis-pubsub
Author: Antje Schremmer
Author-email: antje.schremmer@dwd.de
Maintainer: Tom Kralidis
Maintainer-email: tomkraldis@gmail.com
License: Apache Software License
Keywords: WIS2 PubSub broker topic
Platform: all
Classifier: Development Status :: 4 - Beta
Classifier: Environment :: Console
Classifier: Intended Audience :: Developers
Classifier: Intended Audience :: Science/Research
Classifier: License :: OSI Approved :: Apache Software License
Classifier: Operating System :: OS Independent
Classifier: Programming Language :: Python
License-File: LICENSE
Requires-Dist: click
Requires-Dist: jsonschema
Requires-Dist: paho-mqtt
Requires-Dist: pyyaml
Requires-Dist: requests
Requires-Dist: shapely
Provides-Extra: backend-s3
Requires-Dist: boto3; extra == "backend-s3"
Dynamic: author
Dynamic: author-email
Dynamic: classifier
Dynamic: description
Dynamic: description-content-type
Dynamic: home-page
Dynamic: keywords
Dynamic: license
Dynamic: license-file
Dynamic: maintainer
Dynamic: maintainer-email
Dynamic: platform
Dynamic: provides-extra
Dynamic: requires-dist
Dynamic: summary
